inferless_cli_dev/__init__.py
inferless_cli_dev/__main__.py
inferless_cli_dev/main.py
inferless_cli_dev/prompts/__init__.py
inferless_cli_dev/prompts/deploy.py
inferless_cli_dev/prompts/init.py
inferless_cli_dev/prompts/log.py
inferless_cli_dev/prompts/login.py
inferless_cli_dev/prompts/model.py
inferless_cli_dev/prompts/runtime.py
inferless_cli_dev/prompts/secret.py
inferless_cli_dev/prompts/token.py
inferless_cli_dev/prompts/volume.py
inferless_cli_dev/prompts/workspace.py
inferless_cli_dev/utils/__init__.py
inferless_cli_dev/utils/api.py
inferless_cli_dev/utils/constants.py
inferless_cli_dev/utils/helpers.py
inferless_cli_dev/utils/services.py
inferless_cli_dev/utils/validators.py
inferless_cli_dev-0.1.6.6.dist-info/METADATA
inferless_cli_dev-0.1.6.6.dist-info/WHEEL
inferless_cli_dev-0.1.6.6.dist-info/entry_points.txt
inferless_cli_dev-0.1.6.6.dist-info/RECORD
