Metadata-Version: 2.1
Name: inferless-cli-dev
Version: 0.1.6.6
Summary: 
Author: Naveen
Author-email: naveen@inferless.com
Requires-Python: >=3.8,<4.0
Classifier: Programming Language :: Python :: 3
Classifier: Programming Language :: Python :: 3.8
Classifier: Programming Language :: Python :: 3.9
Classifier: Programming Language :: Python :: 3.10
Classifier: Programming Language :: Python :: 3.11
Classifier: Programming Language :: Python :: 3.12
Requires-Dist: keyring (>=24.3.0,<25.0.0)
Requires-Dist: prompt-toolkit (>=3.0.39,<4.0.0)
Requires-Dist: pyjwt (>=2.8.0,<3.0.0)
Requires-Dist: python-dateutil (>=2.8.2,<3.0.0)
Requires-Dist: requests (>=2.31.0,<3.0.0)
Requires-Dist: ruamel-yaml (>=0.18.5,<0.19.0)
Requires-Dist: sentry-sdk (>=1.35.0,<2.0.0)
Requires-Dist: toml (>=0.10.2,<0.11.0)
Requires-Dist: typer[all] (>=0.9.0,<0.10.0)
